ipython_ollama/__init__.py
ipython_ollama/magic.py
ipython_ollama-0.0.3.dist-info/METADATA
ipython_ollama-0.0.3.dist-info/WHEEL
ipython_ollama-0.0.3.dist-info/licenses/LICENSE
ipython_ollama-0.0.3.dist-info/RECORD
